sagkit/__init__.py
sagkit/jobset_generator.py
sagkit/sag_constructor.py
sagkit/constructors/__init__.py
sagkit/constructors/extended_constructor.py
sagkit/constructors/hybrid_constructor.py
sagkit/constructors/original_constructor.py
sagkit/schedulers/__init__.py
sagkit/schedulers/edf_scheduler.py
sagkit/schedulers/fp_scheduler.py
sagkit/utils/__init__.py
sagkit/utils/job.py
sagkit/utils/state.py
sagkit-0.0.16.dist-info/LICENSE
sagkit-0.0.16.dist-info/METADATA
sagkit-0.0.16.dist-info/WHEEL
sagkit-0.0.16.dist-info/top_level.txt
sagkit-0.0.16.dist-info/RECORD
